rustmap3d/__init__.py
rustmap3d/__init__.pyi
rustmap3d/py.typed
rustmap3d/rustmap3d.cpython-311-x86_64-linux-gnu.so
rustmap3d-0.2.3.dist-info/METADATA
rustmap3d-0.2.3.dist-info/WHEEL
rustmap3d-0.2.3.dist-info/licenses/LICENSE
rustmap3d-0.2.3.dist-info/RECORD
