Metadata-Version: 2.4
Name: rustmap3d
Version: 0.2.3
Classifier: Programming Language :: Rust
Classifier: Programming Language :: Python :: Implementation :: CPython
Classifier: Programming Language :: Python :: Implementation :: PyPy
License-File: LICENSE
License-File: LICENSE
Summary: Python geodetic coordinate conversions written in rust
Author-email: weiler <lucas.l.weiler@leidos.com>, molnar <andrew.b.molnar@leidos.com>
Requires-Python: >=3.8
Project-URL: Homepage, https://github.com/lskyweiler/rustmap3d
